{"nodes": [{"id": "main", "label": "main.rs", "file_type": "code", "source_file": "moa-orchestrator/src/main.rs", "source_location": "L1"}, {"id": "main_args", "label": "Args", "file_type": "code", "source_file": "moa-orchestrator/src/main.rs", "source_location": "L63"}, {"id": "main_main", "label": "main()", "file_type": "code", "source_file": "moa-orchestrator/src/main.rs", "source_location": "L73"}, {"id": "main_probestate", "label": "ProbeState", "file_type": "code", "source_file": "moa-orchestrator/src/main.rs", "source_location": "L188"}, {"id": "main_probestate_new", "label": ".new()", "file_type": "code", "source_file": "moa-orchestrator/src/main.rs", "source_location": "L198"}, {"id": "main_probestate_admin_base_url", "label": ".admin_base_url()", "file_type": "code", "source_file": "moa-orchestrator/src/main.rs", "source_location": "L218"}, {"id": "main_probestate_deregister_on_shutdown", "label": ".deregister_on_shutdown()", "file_type": "code", "source_file": "moa-orchestrator/src/main.rs", "source_location": "L222"}, {"id": "main_probestate_check_ready", "label": ".check_ready()", "file_type": "code", "source_file": "moa-orchestrator/src/main.rs", "source_location": "L226"}, {"id": "main_probestate_fetch_deployments", "label": ".fetch_deployments()", "file_type": "code", "source_file": "moa-orchestrator/src/main.rs", "source_location": "L244"}, {"id": "main_deploymentlistresponse", "label": "DeploymentListResponse", "file_type": "code", "source_file": "moa-orchestrator/src/main.rs", "source_location": "L263"}, {"id": "main_registereddeployment", "label": "RegisteredDeployment", "file_type": "code", "source_file": "moa-orchestrator/src/main.rs", "source_location": "L268"}, {"id": "main_registeredservice", "label": "RegisteredService", "file_type": "code", "source_file": "moa-orchestrator/src/main.rs", "source_location": "L275"}, {"id": "main_live_handler", "label": "live_handler()", "file_type": "code", "source_file": "moa-orchestrator/src/main.rs", "source_location": "L279"}, {"id": "main_ready_handler", "label": "ready_handler()", "file_type": "code", "source_file": "moa-orchestrator/src/main.rs", "source_location": "L283"}, {"id": "main_serve_health_server", "label": "serve_health_server()", "file_type": "code", "source_file": "moa-orchestrator/src/main.rs", "source_location": "L293"}, {"id": "main_spawn_restate_server", "label": "spawn_restate_server()", "file_type": "code", "source_file": "moa-orchestrator/src/main.rs", "source_location": "L309"}, {"id": "main_spawn_health_server", "label": "spawn_health_server()", "file_type": "code", "source_file": "moa-orchestrator/src/main.rs", "source_location": "L321"}, {"id": "main_bind_listener", "label": "bind_listener()", "file_type": "code", "source_file": "moa-orchestrator/src/main.rs", "source_location": "L329"}, {"id": "main_shutdown_signal", "label": "shutdown_signal()", "file_type": "code", "source_file": "moa-orchestrator/src/main.rs", "source_location": "L336"}, {"id": "main_best_effort_deregister", "label": "best_effort_deregister()", "file_type": "code", "source_file": "moa-orchestrator/src/main.rs", "source_location": "L359"}, {"id": "main_env_flag", "label": "env_flag()", "file_type": "code", "source_file": "moa-orchestrator/src/main.rs", "source_location": "L412"}, {"id": "main_env_flag_from_reader", "label": "env_flag_from_reader()", "file_type": "code", "source_file": "moa-orchestrator/src/main.rs", "source_location": "L416"}, {"id": "main_services_registered", "label": "services_registered()", "file_type": "code", "source_file": "moa-orchestrator/src/main.rs", "source_location": "L430"}, {"id": "main_deployment_with_services", "label": "deployment_with_services()", "file_type": "code", "source_file": "moa-orchestrator/src/main.rs", "source_location": "L447"}, {"id": "main_registration_check_requires_all_expected_services", "label": "registration_check_requires_all_expected_services()", "file_type": "code", "source_file": "moa-orchestrator/src/main.rs", "source_location": "L461"}, {"id": "main_registration_check_rejects_partial_deployments", "label": "registration_check_rejects_partial_deployments()", "file_type": "code", "source_file": "moa-orchestrator/src/main.rs", "source_location": "L479"}, {"id": "main_env_flag_understands_common_truthy_and_falsey_values", "label": "env_flag_understands_common_truthy_and_falsey_values()", "file_type": "code", "source_file": "moa-orchestrator/src/main.rs", "source_location": "L486"}], "edges": [{"source": "main", "target": "socketaddr", "relation": "imports_from", "confidence": "EXTRACTED", "source_file": "moa-orchestrator/src/main.rs", "source_location": "L3", "weight": 1.0}, {"source": "main", "target": "arc", "relation": "imports_from", "confidence": "EXTRACTED", "source_file": "moa-orchestrator/src/main.rs", "source_location": "L4", "weight": 1.0}, {"source": "main", "target": "atomic", "relation": "imports_from", "confidence": "EXTRACTED", "source_file": "moa-orchestrator/src/main.rs", "source_location": "L5", "weight": 1.0}, {"source": "main", "target": "duration", "relation": "imports_from", "confidence": "EXTRACTED", "source_file": "moa-orchestrator/src/main.rs", "source_location": "L6", "weight": 1.0}, {"source": "main", "target": "anyhow", "relation": "imports_from", "confidence": "EXTRACTED", "source_file": "moa-orchestrator/src/main.rs", "source_location": "L8", "weight": 1.0}, {"source": "main", "target": "state", "relation": "imports_from", "confidence": "EXTRACTED", "source_file": "moa-orchestrator/src/main.rs", "source_location": "L9", "weight": 1.0}, {"source": "main", "target": "statuscode", "relation": "imports_from", "confidence": "EXTRACTED", "source_file": "moa-orchestrator/src/main.rs", "source_location": "L10", "weight": 1.0}, {"source": "main", "target": "intoresponse", "relation": "imports_from", "confidence": "EXTRACTED", "source_file": "moa-orchestrator/src/main.rs", "source_location": "L11", "weight": 1.0}, {"source": "main", "target": "get", "relation": "imports_from", "confidence": "EXTRACTED", "source_file": "moa-orchestrator/src/main.rs", "source_location": "L12", "weight": 1.0}, {"source": "main", "target": "axum", "relation": "imports_from", "confidence": "EXTRACTED", "source_file": "moa-orchestrator/src/main.rs", "source_location": "L13", "weight": 1.0}, {"source": "main", "target": "parser", "relation": "imports_from", "confidence": "EXTRACTED", "source_file": "moa-orchestrator/src/main.rs", "source_location": "L14", "weight": 1.0}, {"source": "main", "target": "memorystore", "relation": "imports_from", "confidence": "EXTRACTED", "source_file": "moa-orchestrator/src/main.rs", "source_location": "L15", "weight": 1.0}, {"source": "main", "target": "moa_core", "relation": "imports_from", "confidence": "EXTRACTED", "source_file": "moa-orchestrator/src/main.rs", "source_location": "L16", "weight": 1.0}, {"source": "main", "target": "toolrouter", "relation": "imports_from", "confidence": "EXTRACTED", "source_file": "moa-orchestrator/src/main.rs", "source_location": "L17", "weight": 1.0}, {"source": "main", "target": "filememorystore", "relation": "imports_from", "confidence": "EXTRACTED", "source_file": "moa-orchestrator/src/main.rs", "source_location": "L18", "weight": 1.0}, {"source": "main", "target": "moa_orchestrator", "relation": "imports_from", "confidence": "EXTRACTED", "source_file": "moa-orchestrator/src/main.rs", "source_location": "L19", "weight": 1.0}, {"source": "main", "target": "postgressessionstore", "relation": "imports_from", "confidence": "EXTRACTED", "source_file": "moa-orchestrator/src/main.rs", "source_location": "L35", "weight": 1.0}, {"source": "main", "target": "client", "relation": "imports_from", "confidence": "EXTRACTED", "source_file": "moa-orchestrator/src/main.rs", "source_location": "L36", "weight": 1.0}, {"source": "main", "target": "prelude", "relation": "imports_from", "confidence": "EXTRACTED", "source_file": "moa-orchestrator/src/main.rs", "source_location": "L37", "weight": 1.0}, {"source": "main", "target": "deserialize", "relation": "imports_from", "confidence": "EXTRACTED", "source_file": "moa-orchestrator/src/main.rs", "source_location": "L38", "weight": 1.0}, {"source": "main", "target": "pgpooloptions", "relation": "imports_from", "confidence": "EXTRACTED", "source_file": "moa-orchestrator/src/main.rs", "source_location": "L39", "weight": 1.0}, {"source": "main", "target": "tcplistener", "relation": "imports_from", "confidence": "EXTRACTED", "source_file": "moa-orchestrator/src/main.rs", "source_location": "L40", "weight": 1.0}, {"source": "main", "target": "joinhandle", "relation": "imports_from", "confidence": "EXTRACTED", "source_file": "moa-orchestrator/src/main.rs", "source_location": "L41", "weight": 1.0}, {"source": "main", "target": "cancellationtoken", "relation": "imports_from", "confidence": "EXTRACTED", "source_file": "moa-orchestrator/src/main.rs", "source_location": "L42", "weight": 1.0}, {"source": "main", "target": "main_args", "relation": "contains", "confidence": "EXTRACTED", "source_file": "moa-orchestrator/src/main.rs", "source_location": "L63", "weight": 1.0}, {"source": "main", "target": "main_main", "relation": "contains", "confidence": "EXTRACTED", "source_file": "moa-orchestrator/src/main.rs", "source_location": "L73", "weight": 1.0}, {"source": "main", "target": "main_probestate", "relation": "contains", "confidence": "EXTRACTED", "source_file": "moa-orchestrator/src/main.rs", "source_location": "L188", "weight": 1.0}, {"source": "main_probestate", "target": "main_probestate_new", "relation": "method", "confidence": "EXTRACTED", "source_file": "moa-orchestrator/src/main.rs", "source_location": "L198", "weight": 1.0}, {"source": "main_probestate", "target": "main_probestate_admin_base_url", "relation": "method", "confidence": "EXTRACTED", "source_file": "moa-orchestrator/src/main.rs", "source_location": "L218", "weight": 1.0}, {"source": "main_probestate", "target": "main_probestate_deregister_on_shutdown", "relation": "method", "confidence": "EXTRACTED", "source_file": "moa-orchestrator/src/main.rs", "source_location": "L222", "weight": 1.0}, {"source": "main_probestate", "target": "main_probestate_check_ready", "relation": "method", "confidence": "EXTRACTED", "source_file": "moa-orchestrator/src/main.rs", "source_location": "L226", "weight": 1.0}, {"source": "main_probestate", "target": "main_probestate_fetch_deployments", "relation": "method", "confidence": "EXTRACTED", "source_file": "moa-orchestrator/src/main.rs", "source_location": "L244", "weight": 1.0}, {"source": "main", "target": "main_deploymentlistresponse", "relation": "contains", "confidence": "EXTRACTED", "source_file": "moa-orchestrator/src/main.rs", "source_location": "L263", "weight": 1.0}, {"source": "main", "target": "main_registereddeployment", "relation": "contains", "confidence": "EXTRACTED", "source_file": "moa-orchestrator/src/main.rs", "source_location": "L268", "weight": 1.0}, {"source": "main", "target": "main_registeredservice", "relation": "contains", "confidence": "EXTRACTED", "source_file": "moa-orchestrator/src/main.rs", "source_location": "L275", "weight": 1.0}, {"source": "main", "target": "main_live_handler", "relation": "contains", "confidence": "EXTRACTED", "source_file": "moa-orchestrator/src/main.rs", "source_location": "L279", "weight": 1.0}, {"source": "main", "target": "main_ready_handler", "relation": "contains", "confidence": "EXTRACTED", "source_file": "moa-orchestrator/src/main.rs", "source_location": "L283", "weight": 1.0}, {"source": "main", "target": "main_serve_health_server", "relation": "contains", "confidence": "EXTRACTED", "source_file": "moa-orchestrator/src/main.rs", "source_location": "L293", "weight": 1.0}, {"source": "main", "target": "main_spawn_restate_server", "relation": "contains", "confidence": "EXTRACTED", "source_file": "moa-orchestrator/src/main.rs", "source_location": "L309", "weight": 1.0}, {"source": "main", "target": "main_spawn_health_server", "relation": "contains", "confidence": "EXTRACTED", "source_file": "moa-orchestrator/src/main.rs", "source_location": "L321", "weight": 1.0}, {"source": "main", "target": "main_bind_listener", "relation": "contains", "confidence": "EXTRACTED", "source_file": "moa-orchestrator/src/main.rs", "source_location": "L329", "weight": 1.0}, {"source": "main", "target": "main_shutdown_signal", "relation": "contains", "confidence": "EXTRACTED", "source_file": "moa-orchestrator/src/main.rs", "source_location": "L336", "weight": 1.0}, {"source": "main", "target": "main_best_effort_deregister", "relation": "contains", "confidence": "EXTRACTED", "source_file": "moa-orchestrator/src/main.rs", "source_location": "L359", "weight": 1.0}, {"source": "main", "target": "main_env_flag", "relation": "contains", "confidence": "EXTRACTED", "source_file": "moa-orchestrator/src/main.rs", "source_location": "L412", "weight": 1.0}, {"source": "main", "target": "main_env_flag_from_reader", "relation": "contains", "confidence": "EXTRACTED", "source_file": "moa-orchestrator/src/main.rs", "source_location": "L416", "weight": 1.0}, {"source": "main", "target": "main_services_registered", "relation": "contains", "confidence": "EXTRACTED", "source_file": "moa-orchestrator/src/main.rs", "source_location": "L430", "weight": 1.0}, {"source": "main", "target": "super", "relation": "imports_from", "confidence": "EXTRACTED", "source_file": "moa-orchestrator/src/main.rs", "source_location": "L443", "weight": 1.0}, {"source": "main", "target": "main_deployment_with_services", "relation": "contains", "confidence": "EXTRACTED", "source_file": "moa-orchestrator/src/main.rs", "source_location": "L447", "weight": 1.0}, {"source": "main", "target": "main_registration_check_requires_all_expected_services", "relation": "contains", "confidence": "EXTRACTED", "source_file": "moa-orchestrator/src/main.rs", "source_location": "L461", "weight": 1.0}, {"source": "main", "target": "main_registration_check_rejects_partial_deployments", "relation": "contains", "confidence": "EXTRACTED", "source_file": "moa-orchestrator/src/main.rs", "source_location": "L479", "weight": 1.0}, {"source": "main", "target": "main_env_flag_understands_common_truthy_and_falsey_values", "relation": "contains", "confidence": "EXTRACTED", "source_file": "moa-orchestrator/src/main.rs", "source_location": "L486", "weight": 1.0}, {"source": "main_main", "target": "main_probestate_new", "relation": "calls", "confidence": "EXTRACTED", "source_file": "moa-orchestrator/src/main.rs", "source_location": "L76", "weight": 1.0}, {"source": "main_main", "target": "main_bind_listener", "relation": "calls", "confidence": "EXTRACTED", "source_file": "moa-orchestrator/src/main.rs", "source_location": "L133", "weight": 1.0}, {"source": "main_main", "target": "main_spawn_restate_server", "relation": "calls", "confidence": "EXTRACTED", "source_file": "moa-orchestrator/src/main.rs", "source_location": "L135", "weight": 1.0}, {"source": "main_main", "target": "main_spawn_health_server", "relation": "calls", "confidence": "EXTRACTED", "source_file": "moa-orchestrator/src/main.rs", "source_location": "L137", "weight": 1.0}, {"source": "main_probestate_new", "target": "main_env_flag", "relation": "calls", "confidence": "EXTRACTED", "source_file": "moa-orchestrator/src/main.rs", "source_location": "L213", "weight": 1.0}, {"source": "main_probestate_check_ready", "target": "main_probestate_fetch_deployments", "relation": "calls", "confidence": "EXTRACTED", "source_file": "moa-orchestrator/src/main.rs", "source_location": "L236", "weight": 1.0}, {"source": "main_probestate_check_ready", "target": "main_services_registered", "relation": "calls", "confidence": "EXTRACTED", "source_file": "moa-orchestrator/src/main.rs", "source_location": "L237", "weight": 1.0}, {"source": "main_ready_handler", "target": "main_probestate_check_ready", "relation": "calls", "confidence": "EXTRACTED", "source_file": "moa-orchestrator/src/main.rs", "source_location": "L284", "weight": 1.0}, {"source": "main_serve_health_server", "target": "main_probestate_new", "relation": "calls", "confidence": "EXTRACTED", "source_file": "moa-orchestrator/src/main.rs", "source_location": "L298", "weight": 1.0}, {"source": "main_spawn_restate_server", "target": "main_probestate_new", "relation": "calls", "confidence": "EXTRACTED", "source_file": "moa-orchestrator/src/main.rs", "source_location": "L315", "weight": 1.0}, {"source": "main_spawn_health_server", "target": "main_serve_health_server", "relation": "calls", "confidence": "EXTRACTED", "source_file": "moa-orchestrator/src/main.rs", "source_location": "L326", "weight": 1.0}, {"source": "main_best_effort_deregister", "target": "main_probestate_fetch_deployments", "relation": "calls", "confidence": "EXTRACTED", "source_file": "moa-orchestrator/src/main.rs", "source_location": "L367", "weight": 1.0}, {"source": "main_env_flag", "target": "main_env_flag_from_reader", "relation": "calls", "confidence": "EXTRACTED", "source_file": "moa-orchestrator/src/main.rs", "source_location": "L413", "weight": 1.0}]}