{"nodes": [{"id": "lib", "label": "lib.rs", "file_type": "code", "source_file": "moa-session/src/lib.rs", "source_location": "L1"}, {"id": "lib_create_session_store", "label": "create_session_store()", "file_type": "code", "source_file": "moa-session/src/lib.rs", "source_location": "L22"}], "edges": [{"source": "lib", "target": "arc", "relation": "imports_from", "confidence": "EXTRACTED", "source_file": "moa-session/src/lib.rs", "source_location": "L13", "weight": 1.0}, {"source": "lib", "target": "moa_core", "relation": "imports_from", "confidence": "EXTRACTED", "source_file": "moa-session/src/lib.rs", "source_location": "L15", "weight": 1.0}, {"source": "lib", "target": "fileblobstore", "relation": "imports_from", "confidence": "EXTRACTED", "source_file": "moa-session/src/lib.rs", "source_location": "L17", "weight": 1.0}, {"source": "lib", "target": "neonbranchmanager", "relation": "imports_from", "confidence": "EXTRACTED", "source_file": "moa-session/src/lib.rs", "source_location": "L18", "weight": 1.0}, {"source": "lib", "target": "postgressessionstore", "relation": "imports_from", "confidence": "EXTRACTED", "source_file": "moa-session/src/lib.rs", "source_location": "L19", "weight": 1.0}, {"source": "lib", "target": "lib_create_session_store", "relation": "contains", "confidence": "EXTRACTED", "source_file": "moa-session/src/lib.rs", "source_location": "L22", "weight": 1.0}]}