{"nodes": [{"id": "records", "label": "records.rs", "file_type": "code", "source_file": "crates/moa-lineage/core/src/records.rs", "source_location": "L1"}, {"id": "records_lineageevent", "label": "LineageEvent", "file_type": "code", "source_file": "crates/moa-lineage/core/src/records.rs", "source_location": "L15"}, {"id": "records_recordkind", "label": "RecordKind", "file_type": "code", "source_file": "crates/moa-lineage/core/src/records.rs", "source_location": "L33"}, {"id": "records_recordkind_as_i16", "label": ".as_i16()", "file_type": "code", "source_file": "crates/moa-lineage/core/src/records.rs", "source_location": "L51"}, {"id": "records_retrievallineage", "label": "RetrievalLineage", "file_type": "code", "source_file": "crates/moa-lineage/core/src/records.rs", "source_location": "L58"}, {"id": "records_retrievalstage", "label": "RetrievalStage", "file_type": "code", "source_file": "crates/moa-lineage/core/src/records.rs", "source_location": "L95"}, {"id": "records_vechit", "label": "VecHit", "file_type": "code", "source_file": "crates/moa-lineage/core/src/records.rs", "source_location": "L107"}, {"id": "records_graphpath", "label": "GraphPath", "file_type": "code", "source_file": "crates/moa-lineage/core/src/records.rs", "source_location": "L122"}, {"id": "records_fusedhit", "label": "FusedHit", "file_type": "code", "source_file": "crates/moa-lineage/core/src/records.rs", "source_location": "L139"}, {"id": "records_rerankhit", "label": "RerankHit", "file_type": "code", "source_file": "crates/moa-lineage/core/src/records.rs", "source_location": "L156"}, {"id": "records_stagetimings", "label": "StageTimings", "file_type": "code", "source_file": "crates/moa-lineage/core/src/records.rs", "source_location": "L169"}, {"id": "records_backendintrospection", "label": "BackendIntrospection", "file_type": "code", "source_file": "crates/moa-lineage/core/src/records.rs", "source_location": "L188"}, {"id": "records_pgvectorintrospection", "label": "PgvectorIntrospection", "file_type": "code", "source_file": "crates/moa-lineage/core/src/records.rs", "source_location": "L199"}, {"id": "records_ageintrospection", "label": "AgeIntrospection", "file_type": "code", "source_file": "crates/moa-lineage/core/src/records.rs", "source_location": "L216"}, {"id": "records_turbopufferintrospection", "label": "TurbopufferIntrospection", "file_type": "code", "source_file": "crates/moa-lineage/core/src/records.rs", "source_location": "L227"}, {"id": "records_contextlineage", "label": "ContextLineage", "file_type": "code", "source_file": "crates/moa-lineage/core/src/records.rs", "source_location": "L240"}, {"id": "records_contextchunk", "label": "ContextChunk", "file_type": "code", "source_file": "crates/moa-lineage/core/src/records.rs", "source_location": "L265"}, {"id": "records_truncationevent", "label": "TruncationEvent", "file_type": "code", "source_file": "crates/moa-lineage/core/src/records.rs", "source_location": "L280"}, {"id": "records_generationlineage", "label": "GenerationLineage", "file_type": "code", "source_file": "crates/moa-lineage/core/src/records.rs", "source_location": "L291"}, {"id": "records_tokenusage", "label": "TokenUsage", "file_type": "code", "source_file": "crates/moa-lineage/core/src/records.rs", "source_location": "L326"}, {"id": "records_toolcallsummary", "label": "ToolCallSummary", "file_type": "code", "source_file": "crates/moa-lineage/core/src/records.rs", "source_location": "L339"}, {"id": "records_lineageevent_turn_id", "label": ".turn_id()", "file_type": "code", "source_file": "crates/moa-lineage/core/src/records.rs", "source_location": "L357"}, {"id": "records_lineageevent_record_kind", "label": ".record_kind()", "file_type": "code", "source_file": "crates/moa-lineage/core/src/records.rs", "source_location": "L368"}, {"id": "records_lineage_event_serializes_with_kind_and_record", "label": "lineage_event_serializes_with_kind_and_record()", "file_type": "code", "source_file": "crates/moa-lineage/core/src/records.rs", "source_location": "L388"}], "edges": [{"source": "records", "target": "chrono", "relation": "imports_from", "confidence": "EXTRACTED", "source_file": "crates/moa-lineage/core/src/records.rs", "source_location": "L3", "weight": 1.0}, {"source": "records", "target": "moa_core", "relation": "imports_from", "confidence": "EXTRACTED", "source_file": "crates/moa-lineage/core/src/records.rs", "source_location": "L4", "weight": 1.0}, {"source": "records", "target": "serde", "relation": "imports_from", "confidence": "EXTRACTED", "source_file": "crates/moa-lineage/core/src/records.rs", "source_location": "L5", "weight": 1.0}, {"source": "records", "target": "duration", "relation": "imports_from", "confidence": "EXTRACTED", "source_file": "crates/moa-lineage/core/src/records.rs", "source_location": "L6", "weight": 1.0}, {"source": "records", "target": "uuid", "relation": "imports_from", "confidence": "EXTRACTED", "source_file": "crates/moa-lineage/core/src/records.rs", "source_location": "L7", "weight": 1.0}, {"source": "records", "target": "turnid", "relation": "imports_from", "confidence": "EXTRACTED", "source_file": "crates/moa-lineage/core/src/records.rs", "source_location": "L9", "weight": 1.0}, {"source": "records", "target": "records_lineageevent", "relation": "contains", "confidence": "EXTRACTED", "source_file": "crates/moa-lineage/core/src/records.rs", "source_location": "L15", "weight": 1.0}, {"source": "records", "target": "records_recordkind", "relation": "contains", "confidence": "EXTRACTED", "source_file": "crates/moa-lineage/core/src/records.rs", "source_location": "L33", "weight": 1.0}, {"source": "records_recordkind", "target": "records_recordkind_as_i16", "relation": "method", "confidence": "EXTRACTED", "source_file": "crates/moa-lineage/core/src/records.rs", "source_location": "L51", "weight": 1.0}, {"source": "records", "target": "records_retrievallineage", "relation": "contains", "confidence": "EXTRACTED", "source_file": "crates/moa-lineage/core/src/records.rs", "source_location": "L58", "weight": 1.0}, {"source": "records", "target": "records_retrievalstage", "relation": "contains", "confidence": "EXTRACTED", "source_file": "crates/moa-lineage/core/src/records.rs", "source_location": "L95", "weight": 1.0}, {"source": "records", "target": "records_vechit", "relation": "contains", "confidence": "EXTRACTED", "source_file": "crates/moa-lineage/core/src/records.rs", "source_location": "L107", "weight": 1.0}, {"source": "records", "target": "records_graphpath", "relation": "contains", "confidence": "EXTRACTED", "source_file": "crates/moa-lineage/core/src/records.rs", "source_location": "L122", "weight": 1.0}, {"source": "records", "target": "records_fusedhit", "relation": "contains", "confidence": "EXTRACTED", "source_file": "crates/moa-lineage/core/src/records.rs", "source_location": "L139", "weight": 1.0}, {"source": "records", "target": "records_rerankhit", "relation": "contains", "confidence": "EXTRACTED", "source_file": "crates/moa-lineage/core/src/records.rs", "source_location": "L156", "weight": 1.0}, {"source": "records", "target": "records_stagetimings", "relation": "contains", "confidence": "EXTRACTED", "source_file": "crates/moa-lineage/core/src/records.rs", "source_location": "L169", "weight": 1.0}, {"source": "records", "target": "records_backendintrospection", "relation": "contains", "confidence": "EXTRACTED", "source_file": "crates/moa-lineage/core/src/records.rs", "source_location": "L188", "weight": 1.0}, {"source": "records", "target": "records_pgvectorintrospection", "relation": "contains", "confidence": "EXTRACTED", "source_file": "crates/moa-lineage/core/src/records.rs", "source_location": "L199", "weight": 1.0}, {"source": "records", "target": "records_ageintrospection", "relation": "contains", "confidence": "EXTRACTED", "source_file": "crates/moa-lineage/core/src/records.rs", "source_location": "L216", "weight": 1.0}, {"source": "records", "target": "records_turbopufferintrospection", "relation": "contains", "confidence": "EXTRACTED", "source_file": "crates/moa-lineage/core/src/records.rs", "source_location": "L227", "weight": 1.0}, {"source": "records", "target": "records_contextlineage", "relation": "contains", "confidence": "EXTRACTED", "source_file": "crates/moa-lineage/core/src/records.rs", "source_location": "L240", "weight": 1.0}, {"source": "records", "target": "records_contextchunk", "relation": "contains", "confidence": "EXTRACTED", "source_file": "crates/moa-lineage/core/src/records.rs", "source_location": "L265", "weight": 1.0}, {"source": "records", "target": "records_truncationevent", "relation": "contains", "confidence": "EXTRACTED", "source_file": "crates/moa-lineage/core/src/records.rs", "source_location": "L280", "weight": 1.0}, {"source": "records", "target": "records_generationlineage", "relation": "contains", "confidence": "EXTRACTED", "source_file": "crates/moa-lineage/core/src/records.rs", "source_location": "L291", "weight": 1.0}, {"source": "records", "target": "records_tokenusage", "relation": "contains", "confidence": "EXTRACTED", "source_file": "crates/moa-lineage/core/src/records.rs", "source_location": "L326", "weight": 1.0}, {"source": "records", "target": "records_toolcallsummary", "relation": "contains", "confidence": "EXTRACTED", "source_file": "crates/moa-lineage/core/src/records.rs", "source_location": "L339", "weight": 1.0}, {"source": "records_lineageevent", "target": "records_lineageevent_turn_id", "relation": "method", "confidence": "EXTRACTED", "source_file": "crates/moa-lineage/core/src/records.rs", "source_location": "L357", "weight": 1.0}, {"source": "records_lineageevent", "target": "records_lineageevent_record_kind", "relation": "method", "confidence": "EXTRACTED", "source_file": "crates/moa-lineage/core/src/records.rs", "source_location": "L368", "weight": 1.0}, {"source": "records", "target": "utc", "relation": "imports_from", "confidence": "EXTRACTED", "source_file": "crates/moa-lineage/core/src/records.rs", "source_location": "L382", "weight": 1.0}, {"source": "records", "target": "moa_core", "relation": "imports_from", "confidence": "EXTRACTED", "source_file": "crates/moa-lineage/core/src/records.rs", "source_location": "L383", "weight": 1.0}, {"source": "records", "target": "super", "relation": "imports_from", "confidence": "EXTRACTED", "source_file": "crates/moa-lineage/core/src/records.rs", "source_location": "L385", "weight": 1.0}, {"source": "records", "target": "records_lineage_event_serializes_with_kind_and_record", "relation": "contains", "confidence": "EXTRACTED", "source_file": "crates/moa-lineage/core/src/records.rs", "source_location": "L388", "weight": 1.0}]}