{"nodes": [{"id": "api", "label": "api.rs", "file_type": "code", "source_file": "moa-cli/src/api.rs", "source_location": "L1"}, {"id": "api_apistate", "label": "ApiState", "file_type": "code", "source_file": "moa-cli/src/api.rs", "source_location": "L28"}, {"id": "api_build_api_router", "label": "build_api_router()", "file_type": "code", "source_file": "moa-cli/src/api.rs", "source_location": "L34"}, {"id": "api_start_api_server", "label": "start_api_server()", "file_type": "code", "source_file": "moa-cli/src/api.rs", "source_location": "L42"}, {"id": "api_health", "label": "health()", "file_type": "code", "source_file": "moa-cli/src/api.rs", "source_location": "L68"}, {"id": "api_session_stream", "label": "session_stream()", "file_type": "code", "source_file": "moa-cli/src/api.rs", "source_location": "L72"}, {"id": "api_runtime_event_stream", "label": "runtime_event_stream()", "file_type": "code", "source_file": "moa-cli/src/api.rs", "source_location": "L88"}, {"id": "api_stuborchestrator", "label": "StubOrchestrator", "file_type": "code", "source_file": "moa-cli/src/api.rs", "source_location": "L145"}, {"id": "api_stuborchestrator_start_session", "label": ".start_session()", "file_type": "code", "source_file": "moa-cli/src/api.rs", "source_location": "L152"}, {"id": "api_stuborchestrator_resume_session", "label": ".resume_session()", "file_type": "code", "source_file": "moa-cli/src/api.rs", "source_location": "L159"}, {"id": "api_stuborchestrator_signal", "label": ".signal()", "file_type": "code", "source_file": "moa-cli/src/api.rs", "source_location": "L163"}, {"id": "api_stuborchestrator_list_sessions", "label": ".list_sessions()", "file_type": "code", "source_file": "moa-cli/src/api.rs", "source_location": "L171"}, {"id": "api_stuborchestrator_observe", "label": ".observe()", "file_type": "code", "source_file": "moa-cli/src/api.rs", "source_location": "L178"}, {"id": "api_stuborchestrator_observe_runtime", "label": ".observe_runtime()", "file_type": "code", "source_file": "moa-cli/src/api.rs", "source_location": "L186"}, {"id": "api_stuborchestrator_schedule_cron", "label": ".schedule_cron()", "file_type": "code", "source_file": "moa-cli/src/api.rs", "source_location": "L197"}, {"id": "api_health_endpoint_returns_ok", "label": "health_endpoint_returns_ok()", "file_type": "code", "source_file": "moa-cli/src/api.rs", "source_location": "L203"}, {"id": "api_session_stream_returns_sse_content_type", "label": "session_stream_returns_sse_content_type()", "file_type": "code", "source_file": "moa-cli/src/api.rs", "source_location": "L224"}, {"id": "api_session_stream_returns_not_found_when_runtime_is_unavailable", "label": "session_stream_returns_not_found_when_runtime_is_unavailable()", "file_type": "code", "source_file": "moa-cli/src/api.rs", "source_location": "L257"}, {"id": "api_two_sse_subscribers_receive_the_same_runtime_event", "label": "two_sse_subscribers_receive_the_same_runtime_event()", "file_type": "code", "source_file": "moa-cli/src/api.rs", "source_location": "L282"}, {"id": "api_session_stream_emits_gap_event_when_runtime_subscriber_lags", "label": "session_stream_emits_gap_event_when_runtime_subscriber_lags()", "file_type": "code", "source_file": "moa-cli/src/api.rs", "source_location": "L330"}], "edges": [{"source": "api", "target": "infallible", "relation": "imports_from", "confidence": "EXTRACTED", "source_file": "moa-cli/src/api.rs", "source_location": "L3", "weight": 1.0}, {"source": "api", "target": "arc", "relation": "imports_from", "confidence": "EXTRACTED", "source_file": "moa-cli/src/api.rs", "source_location": "L4", "weight": 1.0}, {"source": "api", "target": "duration", "relation": "imports_from", "confidence": "EXTRACTED", "source_file": "moa-cli/src/api.rs", "source_location": "L5", "weight": 1.0}, {"source": "api", "target": "anyhow", "relation": "imports_from", "confidence": "EXTRACTED", "source_file": "moa-cli/src/api.rs", "source_location": "L7", "weight": 1.0}, {"source": "api", "target": "stream", "relation": "imports_from", "confidence": "EXTRACTED", "source_file": "moa-cli/src/api.rs", "source_location": "L8", "weight": 1.0}, {"source": "api", "target": "extract", "relation": "imports_from", "confidence": "EXTRACTED", "source_file": "moa-cli/src/api.rs", "source_location": "L9", "weight": 1.0}, {"source": "api", "target": "statuscode", "relation": "imports_from", "confidence": "EXTRACTED", "source_file": "moa-cli/src/api.rs", "source_location": "L10", "weight": 1.0}, {"source": "api", "target": "intoresponse", "relation": "imports_from", "confidence": "EXTRACTED", "source_file": "moa-cli/src/api.rs", "source_location": "L11", "weight": 1.0}, {"source": "api", "target": "sse", "relation": "imports_from", "confidence": "EXTRACTED", "source_file": "moa-cli/src/api.rs", "source_location": "L12", "weight": 1.0}, {"source": "api", "target": "get", "relation": "imports_from", "confidence": "EXTRACTED", "source_file": "moa-cli/src/api.rs", "source_location": "L13", "weight": 1.0}, {"source": "api", "target": "axum", "relation": "imports_from", "confidence": "EXTRACTED", "source_file": "moa-cli/src/api.rs", "source_location": "L14", "weight": 1.0}, {"source": "api", "target": "stream", "relation": "imports_from", "confidence": "EXTRACTED", "source_file": "moa-cli/src/api.rs", "source_location": "L15", "weight": 1.0}, {"source": "api", "target": "moa_core", "relation": "imports_from", "confidence": "EXTRACTED", "source_file": "moa-cli/src/api.rs", "source_location": "L16", "weight": 1.0}, {"source": "api", "target": "json", "relation": "imports_from", "confidence": "EXTRACTED", "source_file": "moa-cli/src/api.rs", "source_location": "L20", "weight": 1.0}, {"source": "api", "target": "tcplistener", "relation": "imports_from", "confidence": "EXTRACTED", "source_file": "moa-cli/src/api.rs", "source_location": "L21", "weight": 1.0}, {"source": "api", "target": "sync", "relation": "imports_from", "confidence": "EXTRACTED", "source_file": "moa-cli/src/api.rs", "source_location": "L22", "weight": 1.0}, {"source": "api", "target": "joinhandle", "relation": "imports_from", "confidence": "EXTRACTED", "source_file": "moa-cli/src/api.rs", "source_location": "L23", "weight": 1.0}, {"source": "api", "target": "uuid", "relation": "imports_from", "confidence": "EXTRACTED", "source_file": "moa-cli/src/api.rs", "source_location": "L24", "weight": 1.0}, {"source": "api", "target": "api_apistate", "relation": "contains", "confidence": "EXTRACTED", "source_file": "moa-cli/src/api.rs", "source_location": "L28", "weight": 1.0}, {"source": "api", "target": "api_build_api_router", "relation": "contains", "confidence": "EXTRACTED", "source_file": "moa-cli/src/api.rs", "source_location": "L34", "weight": 1.0}, {"source": "api", "target": "api_start_api_server", "relation": "contains", "confidence": "EXTRACTED", "source_file": "moa-cli/src/api.rs", "source_location": "L42", "weight": 1.0}, {"source": "api", "target": "api_health", "relation": "contains", "confidence": "EXTRACTED", "source_file": "moa-cli/src/api.rs", "source_location": "L68", "weight": 1.0}, {"source": "api", "target": "api_session_stream", "relation": "contains", "confidence": "EXTRACTED", "source_file": "moa-cli/src/api.rs", "source_location": "L72", "weight": 1.0}, {"source": "api", "target": "api_runtime_event_stream", "relation": "contains", "confidence": "EXTRACTED", "source_file": "moa-cli/src/api.rs", "source_location": "L88", "weight": 1.0}, {"source": "api", "target": "arc", "relation": "imports_from", "confidence": "EXTRACTED", "source_file": "moa-cli/src/api.rs", "source_location": "L128", "weight": 1.0}, {"source": "api", "target": "duration", "relation": "imports_from", "confidence": "EXTRACTED", "source_file": "moa-cli/src/api.rs", "source_location": "L129", "weight": 1.0}, {"source": "api", "target": "result", "relation": "imports_from", "confidence": "EXTRACTED", "source_file": "moa-cli/src/api.rs", "source_location": "L131", "weight": 1.0}, {"source": "api", "target": "async_trait", "relation": "imports_from", "confidence": "EXTRACTED", "source_file": "moa-cli/src/api.rs", "source_location": "L132", "weight": 1.0}, {"source": "api", "target": "streamext", "relation": "imports_from", "confidence": "EXTRACTED", "source_file": "moa-cli/src/api.rs", "source_location": "L133", "weight": 1.0}, {"source": "api", "target": "moa_core", "relation": "imports_from", "confidence": "EXTRACTED", "source_file": "moa-cli/src/api.rs", "source_location": "L134", "weight": 1.0}, {"source": "api", "target": "content_type", "relation": "imports_from", "confidence": "EXTRACTED", "source_file": "moa-cli/src/api.rs", "source_location": "L139", "weight": 1.0}, {"source": "api", "target": "broadcast", "relation": "imports_from", "confidence": "EXTRACTED", "source_file": "moa-cli/src/api.rs", "source_location": "L140", "weight": 1.0}, {"source": "api", "target": "super", "relation": "imports_from", "confidence": "EXTRACTED", "source_file": "moa-cli/src/api.rs", "source_location": "L142", "weight": 1.0}, {"source": "api", "target": "api_stuborchestrator", "relation": "contains", "confidence": "EXTRACTED", "source_file": "moa-cli/src/api.rs", "source_location": "L145", "weight": 1.0}, {"source": "api_stuborchestrator", "target": "api_stuborchestrator_start_session", "relation": "method", "confidence": "EXTRACTED", "source_file": "moa-cli/src/api.rs", "source_location": "L152", "weight": 1.0}, {"source": "api_stuborchestrator", "target": "api_stuborchestrator_resume_session", "relation": "method", "confidence": "EXTRACTED", "source_file": "moa-cli/src/api.rs", "source_location": "L159", "weight": 1.0}, {"source": "api_stuborchestrator", "target": "api_stuborchestrator_signal", "relation": "method", "confidence": "EXTRACTED", "source_file": "moa-cli/src/api.rs", "source_location": "L163", "weight": 1.0}, {"source": "api_stuborchestrator", "target": "api_stuborchestrator_list_sessions", "relation": "method", "confidence": "EXTRACTED", "source_file": "moa-cli/src/api.rs", "source_location": "L171", "weight": 1.0}, {"source": "api_stuborchestrator", "target": "api_stuborchestrator_observe", "relation": "method", "confidence": "EXTRACTED", "source_file": "moa-cli/src/api.rs", "source_location": "L178", "weight": 1.0}, {"source": "api_stuborchestrator", "target": "api_stuborchestrator_observe_runtime", "relation": "method", "confidence": "EXTRACTED", "source_file": "moa-cli/src/api.rs", "source_location": "L186", "weight": 1.0}, {"source": "api_stuborchestrator", "target": "api_stuborchestrator_schedule_cron", "relation": "method", "confidence": "EXTRACTED", "source_file": "moa-cli/src/api.rs", "source_location": "L197", "weight": 1.0}, {"source": "api", "target": "api_health_endpoint_returns_ok", "relation": "contains", "confidence": "EXTRACTED", "source_file": "moa-cli/src/api.rs", "source_location": "L203", "weight": 1.0}, {"source": "api", "target": "api_session_stream_returns_sse_content_type", "relation": "contains", "confidence": "EXTRACTED", "source_file": "moa-cli/src/api.rs", "source_location": "L224", "weight": 1.0}, {"source": "api", "target": "api_session_stream_returns_not_found_when_runtime_is_unavailable", "relation": "contains", "confidence": "EXTRACTED", "source_file": "moa-cli/src/api.rs", "source_location": "L257", "weight": 1.0}, {"source": "api", "target": "api_two_sse_subscribers_receive_the_same_runtime_event", "relation": "contains", "confidence": "EXTRACTED", "source_file": "moa-cli/src/api.rs", "source_location": "L282", "weight": 1.0}, {"source": "api", "target": "api_session_stream_emits_gap_event_when_runtime_subscriber_lags", "relation": "contains", "confidence": "EXTRACTED", "source_file": "moa-cli/src/api.rs", "source_location": "L330", "weight": 1.0}, {"source": "api_start_api_server", "target": "api_build_api_router", "relation": "calls", "confidence": "EXTRACTED", "source_file": "moa-cli/src/api.rs", "source_location": "L51", "weight": 1.0}, {"source": "api_session_stream", "target": "api_stuborchestrator_observe_runtime", "relation": "calls", "confidence": "EXTRACTED", "source_file": "moa-cli/src/api.rs", "source_location": "L77", "weight": 1.0}, {"source": "api_session_stream", "target": "api_runtime_event_stream", "relation": "calls", "confidence": "EXTRACTED", "source_file": "moa-cli/src/api.rs", "source_location": "L84", "weight": 1.0}, {"source": "api_health_endpoint_returns_ok", "target": "api_build_api_router", "relation": "calls", "confidence": "EXTRACTED", "source_file": "moa-cli/src/api.rs", "source_location": "L207", "weight": 1.0}, {"source": "api_session_stream_returns_sse_content_type", "target": "api_build_api_router", "relation": "calls", "confidence": "EXTRACTED", "source_file": "moa-cli/src/api.rs", "source_location": "L228", "weight": 1.0}, {"source": "api_session_stream_returns_not_found_when_runtime_is_unavailable", "target": "api_build_api_router", "relation": "calls", "confidence": "EXTRACTED", "source_file": "moa-cli/src/api.rs", "source_location": "L261", "weight": 1.0}, {"source": "api_two_sse_subscribers_receive_the_same_runtime_event", "target": "api_build_api_router", "relation": "calls", "confidence": "EXTRACTED", "source_file": "moa-cli/src/api.rs", "source_location": "L286", "weight": 1.0}, {"source": "api_session_stream_emits_gap_event_when_runtime_subscriber_lags", "target": "api_build_api_router", "relation": "calls", "confidence": "EXTRACTED", "source_file": "moa-cli/src/api.rs", "source_location": "L334", "weight": 1.0}]}